{
  "model": "llava:34b-v1.6",
  "created_at": "2024-06-10T17:52:21.049256751Z",
  "response": "The image shows a dramatic and somewhat abstract landscape. It appears to be taken during sunset or sunrise, given the warm hues of the sky. The horizon is blurred, which gives the photo an artistic feel, blurring the lines between the sky and the sea or a large body of water. There are silhouettes that could be interpreted as reed beds or perhaps structures such as boats, but they are not clearly defined due to the camera's motion during the shot, resulting in motion blur. The overall effect is quite evocative and moody, with a sense of depth created by the play of light and shadow across the scene.",
  "done": true,
  "done_reason": "stop",
  "context": [
    1581,
    59705,
    622,
    59593,
    5858,
    46826,
    10707,
    144,
    59666,
    59705,
    622,
    59593,
    701,
    46826,
    144,
    59666,
    59705,
    622,
    59593,
    5858,
    46826,
    3903,
    144,
    5697,
    620,
    594,
    719,
    4652,
    100,
    59666,
    59705,
    622,
    59593,
    701,
    46826,
    144,
    59666,
    59705,
    622,
    59593,
    5858,
    46826,
    765,
    13611,
    144,
    1263,
    2728,
    2587,
    562,
    14868,
    597,
    8653,
    14448,
    12554,
    98,
    983,
    5405,
    592,
    629,
    2955,
    1773,
    32668,
    705,
    54141,
    97,
    1858,
    567,
    5384,
    602,
    1281,
    593,
    567,
    8697,
    98,
    707,
    15260,
    620,
    55815,
    97,
    878,
    3641,
    567,
    5631,
    663,
    19763,
    1562,
    97,
    20874,
    1137,
    567,
    3661,
    1397,
    567,
    8697,
    597,
    567,
    8166,
    705,
    562,
    2014,
    2534,
    593,
    2127,
    98,
    1889,
    678,
    40120,
    29695,
    639,
    1158,
    629,
    18832,
    659,
    612,
    584,
    20165,
    705,
    5403,
    7960,
    1253,
    659,
    24008,
    97,
    796,
    838,
    678,
    728,
    5396,
    3712,
    2436,
    592,
    567,
    5490,
    59610,
    59575,
    6106,
    1773,
    567,
    4709,
    97,
    6836,
    594,
    6106,
    20874,
    98,
    707,
    5043,
    1646,
    620,
    2865,
    921,
    39603,
    597,
    12692,
    59587,
    97,
    651,
    562,
    3345,
    593,
    6928,
    3527,
    737,
    567,
    1205,
    593,
    1961,
    597,
    14950,
    2656,
    567,
    5753,
    98
  ],
  "total_duration": 64477686955,
  "load_duration": 5071076,
  "prompt_eval_duration": 16316445000,
  "eval_count": 134,
  "eval_duration": 48082603000
}
