{
  "model": "llava:34b-v1.6",
  "created_at": "2024-06-10T18:00:53.810322616Z",
  "response": "The image shows a breathtaking view of Antelope Canyon, which is located in Arizona's Glen Canyon National Recreation Area. The photo captures the iconic slot canyon known for its wave-like structure and light beams that occur at certain times of the year. These light beams are created by the alignment of sunlight with the slot canyon's narrow passageways. The perspective in this image suggests it was taken from an elevated vantage point, providing a panoramic view of the canyon and its unique geological formations. This is a popular tourist destination known for its photography opportunities.",
  "done": true,
  "done_reason": "stop",
  "context": [
    1581,
    59705,
    622,
    59593,
    5858,
    46826,
    10707,
    144,
    59666,
    59705,
    622,
    59593,
    701,
    46826,
    144,
    59666,
    59705,
    622,
    59593,
    5858,
    46826,
    3903,
    144,
    5697,
    620,
    594,
    719,
    4652,
    100,
    59666,
    59705,
    622,
    59593,
    701,
    46826,
    144,
    59666,
    59705,
    622,
    59593,
    5858,
    46826,
    765,
    13611,
    144,
    1263,
    2728,
    2587,
    562,
    38692,
    2321,
    593,
    7154,
    605,
    1906,
    32188,
    97,
    878,
    620,
    4961,
    594,
    13464,
    59610,
    59575,
    29094,
    32188,
    3750,
    47735,
    13686,
    98,
    707,
    5631,
    24400,
    567,
    21249,
    12744,
    748,
    30872,
    2549,
    631,
    1034,
    5457,
    59594,
    3365,
    3307,
    597,
    1961,
    27243,
    639,
    4522,
    702,
    2405,
    2056,
    593,
    567,
    990,
    98,
    2789,
    1961,
    27243,
    678,
    3527,
    737,
    567,
    17434,
    593,
    29389,
    651,
    567,
    12744,
    748,
    30872,
    59610,
    59575,
    9448,
    15072,
    1605,
    98,
    707,
    7850,
    594,
    719,
    2728,
    8441,
    648,
    717,
    2955,
    742,
    663,
    25448,
    713,
    727,
    807,
    1330,
    97,
    5335,
    562,
    43645,
    18337,
    2321,
    593,
    567,
    748,
    30872,
    597,
    1034,
    3888,
    4256,
    3568,
    57573,
    98,
    1117,
    620,
    562,
    3828,
    21276,
    11513,
    2549,
    631,
    1034,
    14314,
    6772,
    98
  ],
  "total_duration": 59897667516,
  "load_duration": 3984799,
  "prompt_eval_duration": 16136177000,
  "eval_count": 124,
  "eval_duration": 43679170000
}
